offsets_db_data/__init__.py
offsets_db_data/_version.py
offsets_db_data/apx.py
offsets_db_data/arb.py
offsets_db_data/catalog.yaml
offsets_db_data/common.py
offsets_db_data/credits.py
offsets_db_data/data.py
offsets_db_data/gld.py
offsets_db_data/models.py
offsets_db_data/openrefine.py
offsets_db_data/pipeline_utils.py
offsets_db_data/projects.py
offsets_db_data/py.typed
offsets_db_data/registry.py
offsets_db_data/vcs.py
offsets_db_data/configs/all-protocol-mapping.json
offsets_db_data/configs/beneficiary-mappings.json
offsets_db_data/configs/credits-raw-columns-mapping.json
offsets_db_data/configs/projects-raw-columns-mapping.json
offsets_db_data-2025.3.28.dist-info/licenses/LICENSE
offsets_db_data-2025.3.28.dist-info/METADATA
offsets_db_data-2025.3.28.dist-info/WHEEL
offsets_db_data-2025.3.28.dist-info/entry_points.txt
offsets_db_data-2025.3.28.dist-info/top_level.txt
offsets_db_data-2025.3.28.dist-info/RECORD
