Metadata-Version: 2.4
Name: offsets-db-data
Version: 2025.3.28
Summary: Monitoring the global carbon market
Author-email: CarbonPlan <tech@carbonplan.org>
License: MIT
Project-URL: database web tool, https://carbonplan.org/research/offsets-db
Project-URL: documentation, https://offsets-db-data.readthedocs.io/
Project-URL: explainer, https://carbonplan.org/research/offsets-db-explainer
Project-URL: repository, https://github.com/carbonplan/offsets-db-data
Classifier: Development Status :: 4 - Beta
Classifier: Intended Audience :: Science/Research
Classifier: License :: OSI Approved :: MIT License
Classifier: Operating System :: OS Independent
Classifier: Programming Language :: Python :: 3
Classifier: Programming Language :: Python :: 3.10
Classifier: Programming Language :: Python :: 3.11
Classifier: Programming Language :: Python :: 3.12
Classifier: Programming Language :: Python
Classifier: Topic :: Scientific/Engineering
Requires-Python: >=3.10
License-File: LICENSE
Requires-Dist: country_converter==1.0.0
Requires-Dist: dask==2025.2.0
Requires-Dist: fastparquet==2024.11
Requires-Dist: fsspec==2025.2.0
Requires-Dist: intake-parquet>=0.3.0
Requires-Dist: intake<2
Requires-Dist: pandas==2.2.2
Requires-Dist: pandera==0.23
Requires-Dist: pydantic==2.10.*
Requires-Dist: pyjanitor==0.23.*
Requires-Dist: requests>=2.31.0
Requires-Dist: s3fs==2025.2.0
Requires-Dist: universal_pathlib>=0.1.3
Requires-Dist: numpy>=2
Requires-Dist: typer>=0.15.2
Dynamic: license-file
